pushgateway/__init__.py
pushgateway/config.py
pushgateway/gateway.py
pushgateway/openhab.py
pushgateway/unit.py
pushgateway/webthing.py
pushgateway-0.1.13.dist-info/LICENSE
pushgateway-0.1.13.dist-info/METADATA
pushgateway-0.1.13.dist-info/WHEEL
pushgateway-0.1.13.dist-info/entry_points.txt
pushgateway-0.1.13.dist-info/top_level.txt
pushgateway-0.1.13.dist-info/RECORD
